{
	"hidden": true,
	"type": "origins:multiple",
	"helmet_boost": {
		"type": "origins:conditioned_attribute",
		"tick_rate": 20,
		"update_health": true,
		"modifiers": [
			{
				"attribute": "minecraft:generic.knockback_resistance",
				"operation": "addition",
				"value": 1
			},
			{
				"attribute": "minecraft:generic.max_health",
				"operation": "addition",
				"value": 1
			}
		],
		"condition": {
			"type": "origins:equipped_item",
			"equipment_slot": "head",
			"item_condition": {
				"type": "origins:ingredient",
				"ingredient": {
					"tag": "medievalorigins:orichalcum_gear"
				}
			}
		}
	},
	"chestplate_boost": {
		"type": "origins:conditioned_attribute",
		"tick_rate": 20,
		"update_health": true,
		"modifiers": [
			{
				"attribute": "minecraft:generic.knockback_resistance",
				"operation": "addition",
				"value": 1
			},
			{
				"attribute": "minecraft:generic.max_health",
				"operation": "addition",
				"value": 1
			}
		],
		"condition": {
			"type": "origins:equipped_item",
			"equipment_slot": "chest",
			"item_condition": {
				"type": "origins:ingredient",
				"ingredient": {
					"tag": "medievalorigins:orichalcum_gear"
				}
			}
		}
	},
	"leggings_boost": {
		"type": "origins:conditioned_attribute",
		"tick_rate": 20,
		"update_health": true,
		"modifiers": [
			{
				"attribute": "minecraft:generic.knockback_resistance",
				"operation": "addition",
				"value": 1
			},
			{
				"attribute": "minecraft:generic.max_health",
				"operation": "addition",
				"value": 1
			}
		],
		"condition": {
			"type": "origins:equipped_item",
			"equipment_slot": "legs",
			"item_condition": {
				"type": "origins:ingredient",
				"ingredient": {
					"tag": "medievalorigins:orichalcum_gear"
				}
			}
		}
	},
	"boots_boost": {
		"type": "origins:conditioned_attribute",
		"tick_rate": 20,
		"update_health": true,
		"modifiers": [
			{
				"attribute": "minecraft:generic.knockback_resistance",
				"operation": "addition",
				"value": 1
			},
			{
				"attribute": "minecraft:generic.max_health",
				"operation": "addition",
				"value": 1
			}
		],
		"condition": {
			"type": "origins:equipped_item",
			"equipment_slot": "feet",
			"item_condition": {
				"type": "origins:ingredient",
				"ingredient": {
					"tag": "medievalorigins:orichalcum_gear"
				}
			}
		}
	},
	"armor_tooltip": {
		"type": "apoli:tooltip",
		"item_condition": {
			"type": "origins:and",
			"conditions": [
				{
					"type": "apoli:ingredient",
					"ingredient": {
						"tag": "medievalorigins:orichalcum_gear"
					}
				},
				{
					"type": "apoli:ingredient",
					"ingredient": {
						"tag": "c:armor"
					}
				}
			]
		},
		"text": [
			{
				"translate": "power.medievalorigins.ogre/orcish_pride.name",
				"color": "green"
			},
			{
				"text": ":",
				"color": "green"
			},
			{
				"text": "\n+1 ",
				"color": "dark_green"
			},
			{
				"translate": "attribute.name.generic.knockback_resistance",
				"color": "dark_green"
			},
			{
				"text": "\n+1 ",
				"color": "dark_green"
			},
			{
				"translate": "attribute.name.generic.max_health",
				"color": "dark_green"
			}
		]
	}
}